{
  "project_info": {
    "project_number": "322984623660",
    "project_id": "birlik-b9ddc",
    "storage_bucket": "birlik-b9ddc.appspot.com"
  },
  "client": [
    {
      "client_info": {
        "mobilesdk_app_id": "1:322984623660:android:73a7c6e0cb8c96e25e9b89",
        "android_client_info": {
          "package_name": "com.zaurh.durak"
        }
      },
      "oauth_client": [],
      "api_key": [
        {
          "current_key": "AIzaSyAvJSj_wPUSKUNNKRvJM4k8ectFaW31ZTg"
        }
      ],
      "services": {
        "appinvite_service": {
          "other_platform_oauth_client": []
        }
      }
    }
  ],
  "configuration_version": "1"
}